[
  {
    "id": "a18801",
    "german": "das Wetter",
    "english": "weather",
    "category": "weather_seasons",
    "group": "daily_life_basics",
    "tag": "Weather & Seasons",
    "example": "Wie ist das Wetter heute?",
    "difficulty": "easy",
    "isFavorite": false,
    "dari": "هوا"
  },
  {
    "id": "a18802",
    "german": "sonnig",
    "english": "sunny",
    "category": "weather_seasons",
    "group": "daily_life_basics",
    "tag": "Weather & Seasons",
    "example": "Heute ist es sonnig.",
    "difficulty": "easy",
    "isFavorite": false,
    "dari": "آفتابی"
  },
  {
    "id": "a18803",
    "german": "bewölkt",
    "english": "cloudy",
    "category": "weather_seasons",
    "group": "daily_life_basics",
    "tag": "Weather & Seasons",
    "example": "Am Morgen ist es bewölkt.",
    "difficulty": "easy",
    "isFavorite": false,
    "dari": "ابری"
  },
  {
    "id": "a18804",
    "german": "regnerisch",
    "english": "rainy",
    "category": "weather_seasons",
    "group": "daily_life_basics",
    "tag": "Weather & Seasons",
    "example": "Der Tag ist kalt und regnerisch.",
    "difficulty": "easy",
    "isFavorite": false,
    "dari": "بارانی"
  },
  {
    "id": "a18805",
    "german": "windig",
    "english": "windy",
    "category": "weather_seasons",
    "group": "daily_life_basics",
    "tag": "Weather & Seasons",
    "example": "Heute ist es sehr windig.",
    "difficulty": "easy",
    "isFavorite": false,
    "dari": "بادی"
  },
  {
    "id": "a18806",
    "german": "kalt",
    "english": "cold",
    "category": "weather_seasons",
    "group": "daily_life_basics",
    "tag": "Weather & Seasons",
    "example": "Im Winter ist es oft kalt.",
    "difficulty": "easy",
    "isFavorite": false,
    "dari": "سرد"
  },
  {
    "id": "a18807",
    "german": "warm",
    "english": "warm",
    "category": "weather_seasons",
    "group": "daily_life_basics",
    "tag": "Weather & Seasons",
    "example": "Heute ist es angenehm warm.",
    "difficulty": "easy",
    "isFavorite": false,
    "dari": "گرم"
  },
  {
    "id": "a18808",
    "german": "heiß",
    "english": "hot",
    "category": "weather_seasons",
    "group": "daily_life_basics",
    "tag": "Weather & Seasons",
    "example": "Im Juli ist es manchmal sehr heiß.",
    "difficulty": "easy",
    "isFavorite": false,
    "dari": "داغ / خیلی گرم"
  },
  {
    "id": "a18809",
    "german": "der Frühling",
    "english": "spring",
    "category": "weather_seasons",
    "group": "daily_life_basics",
    "tag": "Weather & Seasons",
    "example": "Im Frühling blühen viele Blumen.",
    "difficulty": "easy",
    "isFavorite": false,
    "dari": "بهار"
  },
  {
    "id": "a18810",
    "german": "der Sommer",
    "english": "summer",
    "category": "weather_seasons",
    "group": "daily_life_basics",
    "tag": "Weather & Seasons",
    "example": "Im Sommer fahren viele Leute in Urlaub.",
    "difficulty": "easy",
    "isFavorite": false,
    "dari": "تابستان"
  },
  {
    "id": "a18811",
    "german": "der Herbst",
    "english": "autumn",
    "category": "weather_seasons",
    "group": "daily_life_basics",
    "tag": "Weather & Seasons",
    "example": "Im Herbst fallen die Blätter.",
    "difficulty": "easy",
    "isFavorite": false,
    "dari": "پاییز"
  },
  {
    "id": "a18812",
    "german": "der Winter",
    "english": "winter",
    "category": "weather_seasons",
    "group": "daily_life_basics",
    "tag": "Weather & Seasons",
    "example": "Im Winter schneit es oft.",
    "difficulty": "easy",
    "isFavorite": false,
    "dari": "زمستان"
  },
  {
    "id": "a18813",
    "german": "die Temperatur",
    "english": "temperature",
    "category": "weather_seasons",
    "group": "daily_life_basics",
    "tag": "Weather & Seasons",
    "example": "Die Temperatur liegt bei zehn Grad.",
    "difficulty": "easy",
    "isFavorite": false,
    "dari": "دما"
  },
  {
    "id": "a18814",
    "german": "es regnet",
    "english": "it is raining",
    "category": "weather_seasons",
    "group": "daily_life_basics",
    "tag": "Weather & Seasons",
    "example": "Nimm den Schirm mit, es regnet.",
    "difficulty": "easy",
    "isFavorite": false,
    "dari": "باران می‌بارد"
  },
  {
    "id": "a18815",
    "german": "es schneit",
    "english": "it is snowing",
    "category": "weather_seasons",
    "group": "daily_life_basics",
    "tag": "Weather & Seasons",
    "example": "Heute schneit es in München.",
    "difficulty": "easy",
    "isFavorite": false,
    "dari": "برف می‌بارد"
  },
  {
    "id": "a18816",
    "german": "die Sonne",
    "english": "sun",
    "category": "weather_seasons",
    "group": "daily_life_basics",
    "tag": "Weather & Seasons",
    "example": "Die Sonne scheint stark.",
    "difficulty": "easy",
    "isFavorite": false,
    "dari": "خورشید"
  },
  {
    "id": "a18817",
    "german": "der Regen",
    "english": "rain",
    "category": "weather_seasons",
    "group": "daily_life_basics",
    "tag": "Weather & Seasons",
    "example": "Der Regen beginnt am Nachmittag.",
    "difficulty": "easy",
    "isFavorite": false,
    "dari": "باران"
  },
  {
    "id": "a18818",
    "german": "der Wind",
    "english": "wind",
    "category": "weather_seasons",
    "group": "daily_life_basics",
    "tag": "Weather & Seasons",
    "example": "Der Wind ist heute stark.",
    "difficulty": "easy",
    "isFavorite": false,
    "dari": "باد"
  },
  {
    "id": "a18819",
    "german": "die Wolke",
    "english": "cloud",
    "category": "weather_seasons",
    "group": "daily_life_basics",
    "tag": "Weather & Seasons",
    "example": "Eine dunkle Wolke kommt näher.",
    "difficulty": "easy",
    "isFavorite": false,
    "dari": "ابر"
  },
  {
    "id": "a18820",
    "german": "das Gewitter",
    "english": "thunderstorm",
    "category": "weather_seasons",
    "group": "daily_life_basics",
    "tag": "Weather & Seasons",
    "example": "Am Abend gibt es ein Gewitter.",
    "difficulty": "easy",
    "isFavorite": false,
    "dari": "طوفان"
  },
  {
    "id": "a18821",
    "german": "der Nebel",
    "english": "fog",
    "category": "weather_seasons",
    "group": "daily_life_basics",
    "tag": "Weather & Seasons",
    "example": "Am Morgen gibt es viel Nebel.",
    "difficulty": "easy",
    "isFavorite": false,
    "dari": "مه"
  },
  {
    "id": "a18822",
    "german": "kühl",
    "english": "cool",
    "category": "weather_seasons",
    "group": "daily_life_basics",
    "tag": "Weather & Seasons",
    "example": "Heute Abend ist es kühl.",
    "difficulty": "easy",
    "isFavorite": false,
    "dari": "خنک"
  },
  {
    "id": "a18823",
    "german": "stürmisch",
    "english": "stormy",
    "category": "weather_seasons",
    "group": "daily_life_basics",
    "tag": "Weather & Seasons",
    "example": "Morgen wird es stürmisch.",
    "difficulty": "easy",
    "isFavorite": false,
    "dari": "طوفانی"
  },
  {
    "id": "a18824",
    "german": "der Schnee",
    "english": "snow",
    "category": "weather_seasons",
    "group": "daily_life_basics",
    "tag": "Weather & Seasons",
    "example": "Der Schnee liegt auf der Straße.",
    "difficulty": "easy",
    "isFavorite": false,
    "dari": "برف"
  },
  {
    "id": "a18825",
    "german": "das Grad",
    "english": "degree",
    "category": "weather_seasons",
    "group": "daily_life_basics",
    "tag": "Weather & Seasons",
    "example": "Heute sind es zehn Grad.",
    "difficulty": "easy",
    "isFavorite": false,
    "dari": "درجه"
  },
  {
    "id": "a18826",
    "german": "der Wetterbericht",
    "english": "weather report",
    "category": "weather_seasons",
    "group": "daily_life_basics",
    "tag": "Weather & Seasons",
    "example": "Ich höre den Wetterbericht im Radio.",
    "difficulty": "easy",
    "isFavorite": false,
    "dari": "گزارش هواشناسی"
  },
  {
    "id": "a18827",
    "german": "der Schirm",
    "english": "umbrella",
    "category": "weather_seasons",
    "group": "daily_life_basics",
    "tag": "Weather & Seasons",
    "example": "Nimm bitte einen Schirm mit.",
    "difficulty": "easy",
    "isFavorite": false,
    "dari": "چتر"
  },
  {
    "id": "a18828",
    "german": "das Eis",
    "english": "ice",
    "category": "weather_seasons",
    "group": "daily_life_basics",
    "tag": "Weather & Seasons",
    "example": "Auf der Straße ist Eis.",
    "difficulty": "easy",
    "isFavorite": false,
    "dari": "یخ"
  },
  {
    "id": "a18829",
    "german": "glatt",
    "english": "slippery",
    "category": "weather_seasons",
    "group": "daily_life_basics",
    "tag": "Weather & Seasons",
    "example": "Vorsicht, die Straße ist glatt.",
    "difficulty": "easy",
    "isFavorite": false,
    "dari": "لغزنده"
  },
  {
    "id": "a18830",
    "german": "der Frost",
    "english": "frost",
    "category": "weather_seasons",
    "group": "daily_life_basics",
    "tag": "Weather & Seasons",
    "example": "In der Nacht gibt es Frost.",
    "difficulty": "easy",
    "isFavorite": false,
    "dari": "یخبندان"
  }
]
